okta/__init__.py
okta/api_client.py
okta/api_response.py
okta/client.py
okta/constants.py
okta/error_messages.py
okta/helpers.py
okta/http_client.py
okta/jwt.py
okta/oauth.py
okta/okta_collection.py
okta/okta_object.py
okta/request_executor.py
okta/user_agent.py
okta/utils.py
okta/cache/__init__.py
okta/cache/cache.py
okta/cache/no_op_cache.py
okta/cache/okta_cache.py
okta/config/__init__.py
okta/config/config_setter.py
okta/config/config_validator.py
okta/errors/__init__.py
okta/errors/error.py
okta/errors/http_error.py
okta/errors/okta_api_error.py
okta/exceptions/__init__.py
okta/exceptions/exceptions.py
okta/models/__init__.py
okta/models/acs_endpoint.py
okta/models/activate_factor_request.py
okta/models/app_and_instance_condition_evaluator_app_or_instance.py
okta/models/app_and_instance_policy_rule_condition.py
okta/models/app_instance_policy_rule_condition.py
okta/models/app_link.py
okta/models/app_user.py
okta/models/app_user_credentials.py
okta/models/app_user_password_credential.py
okta/models/application.py
okta/models/application_accessibility.py
okta/models/application_credentials.py
okta/models/application_credentials_o_auth_client.py
okta/models/application_credentials_scheme.py
okta/models/application_credentials_signing.py
okta/models/application_credentials_signing_use.py
okta/models/application_credentials_username_template.py
okta/models/application_group_assignment.py
okta/models/application_licensing.py
okta/models/application_settings.py
okta/models/application_settings_application.py
okta/models/application_settings_notifications.py
okta/models/application_settings_notifications_vpn.py
okta/models/application_settings_notifications_vpn_network.py
okta/models/application_sign_on_mode.py
okta/models/application_visibility.py
okta/models/application_visibility_hide.py
okta/models/assign_role_request.py
okta/models/authentication_provider.py
okta/models/authentication_provider_type.py
okta/models/authorization_server.py
exos_okta-1.2.1.dist-info/LICENSE.md
exos_okta-1.2.1.dist-info/METADATA
exos_okta-1.2.1.dist-info/WHEEL
exos_okta-1.2.1.dist-info/top_level.txt
exos_okta-1.2.1.dist-info/RECORD
