Metadata-Version: 2.1
Name: exos-okta
Version: 1.2.1
Summary: Python SDK for the Okta Management API
Home-page: https://github.com/ypukhta/okta-sdk-python
Author: Okta, Inc.
Author-email: yevgen.pukhta@exosfinancial.com
License: Apache License 2.0
Platform: UNKNOWN
Classifier: Development Status :: 5 - Production/Stable
Classifier: Intended Audience :: Developers
Classifier: Programming Language :: Python
Classifier: Programming Language :: Python :: 3.6
Classifier: Programming Language :: Python :: 3.7
Classifier: Programming Language :: Python :: 3.8
Classifier: License :: OSI Approved :: Apache Software License
Classifier: Topic :: Software Development :: Libraries :: Python Modules
Requires-Python: >=3.6
Requires-Dist: aiohttp
Requires-Dist: flatdict
Requires-Dist: pyyaml
Requires-Dist: xmltodict
Requires-Dist: yarl
Requires-Dist: pycryptodome
Requires-Dist: python-jose
Requires-Dist: aenum
Requires-Dist: pydash
Requires-Dist: flake8
Requires-Dist: pytest
Requires-Dist: pytest-asyncio
Requires-Dist: pytest-mock
Requires-Dist: pytest-recording
Requires-Dist: pyfakefs
